adafruit_circuitpython_midi-1.5.6.dist-info/licenses/LICENSE
adafruit_midi/__init__.py
adafruit_midi/active_sensing.py
adafruit_midi/channel_pressure.py
adafruit_midi/control_change.py
adafruit_midi/control_change_values.py
adafruit_midi/midi_continue.py
adafruit_midi/midi_message.py
adafruit_midi/mtc_quarter_frame.py
adafruit_midi/note_off.py
adafruit_midi/note_on.py
adafruit_midi/pitch_bend.py
adafruit_midi/polyphonic_key_pressure.py
adafruit_midi/program_change.py
adafruit_midi/start.py
adafruit_midi/stop.py
adafruit_midi/system_exclusive.py
adafruit_midi/timing_clock.py
adafruit_circuitpython_midi-1.5.6.dist-info/METADATA
adafruit_circuitpython_midi-1.5.6.dist-info/WHEEL
adafruit_circuitpython_midi-1.5.6.dist-info/top_level.txt
adafruit_circuitpython_midi-1.5.6.dist-info/RECORD
