Metadata-Version: 2.4
Name: adafruit-circuitpython-midi
Version: 1.5.6
Summary: A CircuitPython helper for encoding/decoding MIDI packets over a MIDI or UART connection.
Author-email: Adafruit Industries <circuitpython@adafruit.com>
License: MIT
Project-URL: Homepage, https://github.com/adafruit/Adafruit_CircuitPython_MIDI
Keywords: adafruit,blinka,circuitpython,micropython,midi,uart,encoding,decoding
Classifier: Intended Audience :: Developers
Classifier: Topic :: Software Development :: Libraries
Classifier: Topic :: Software Development :: Embedded Systems
Classifier: Topic :: System :: Hardware
Classifier: License :: OSI Approved :: MIT License
Classifier: Programming Language :: Python :: 3
License-File: LICENSE
Requires-Dist: Adafruit-Blinka
Provides-Extra: optional
Dynamic: license-file
